LICENSE
MANIFEST.in
README.md
pyproject.toml
setup.cfg
setup.py
django_pikpdf/__init__.py
django_pikpdf/admin.py
django_pikpdf/apps.py
django_pikpdf/converter.py
django_pikpdf/models.py
django_pikpdf/views.py
django_pikpdf.egg-info/PKG-INFO
django_pikpdf.egg-info/SOURCES.txt
django_pikpdf.egg-info/dependency_links.txt
django_pikpdf.egg-info/requires.txt
django_pikpdf.egg-info/top_level.txt
django_pikpdf/controllers/__init__.py
django_pikpdf/controllers/api.py
django_pikpdf/controllers/html_transformation.py
django_pikpdf/controllers/validators.py
django_pikpdf/migrations/__init__.py