Metadata-Version: 2.1
Name: django-pikpdf
Version: 0.4.3
Summary: A Django app to convert html to pdf
Home-page: https://www.pikutis.lt/
Author: Tadas Pikutis
Author-email: tadas@pikutis.dev
License: MIT
Classifier: Environment :: Web Environment
Classifier: Framework :: Django
Classifier: Framework :: Django :: 4.2
Classifier: Intended Audience :: Developers
Classifier: License :: OSI Approved :: BSD License
Classifier: Operating System :: OS Independent
Classifier: Programming Language :: Python
Classifier: Programming Language :: Python :: 3
Classifier: Programming Language :: Python :: 3 :: Only
Classifier: Programming Language :: Python :: 3.10
Classifier: Programming Language :: Python :: 3.11
Classifier: Programming Language :: Python :: 3.12
Classifier: Topic :: Internet :: WWW/HTTP
Classifier: Topic :: Internet :: WWW/HTTP :: Dynamic Content
Requires-Python: >=3.10
License-File: LICENSE
Requires-Dist: Django>=4.2
Requires-Dist: requests
Requires-Dist: validators
